Workbook

Sheet RawData
A1: Label | B1: Jan | C1: Feb | D1: Mar | E1: Apr | F1: May | G1: Jun | H1: Jul | I1: Aug | J1: Sep | K1: Oct | L1: Nov | M1: Dec
A2: Units | B2: 997 | C2: 1188 | D2: 1015 | E2: 820 | F2: 932 | G2: 1061 | H2: 1048 | I2: 1007 | J2: 955 | K2: 1044 | L2: 983 | M2: 1098
A3: UnitPrice | B3: 62.83 | C3: 49.37 | D3: 47.79 | E3: 47.79 | F3: 46.9 | G3: 60.99 | H3: 64.75 | I3: 55.65 | J3: 59.1 | K3: 57.04 | L3: 47.94 | M3: 46.98
A4: UnitCost | B4: 26.11 | C4: 37.76 | D4: 29.95 | E4: 33.4 | F4: 30.31 | G4: 29.74 | H4: 34.61 | I4: 28.07 | J4: 33.29 | K4: 31.64 | L4: 32.82 | M4: 25.93
A5: Opex | B5: 9494 | C5: 5115 | D5: 5764 | E5: 10895 | F5: 11882 | G5: 8267 | H5: 10818 | I5: 11757 | J5: 11431 | K5: 10473 | L5: 10122 | M5: 5009
A6: MonthNo | B6: 1 | C6: 2 | D6: 3 | E6: 4 | F6: 5 | G6: 6 | H6: 7 | I6: 8 | J6: 9 | K6: 10 | L6: 11 | M6: 12

Sheet Revenue
A1: Label | B1: Jan | C1: Feb | D1: Mar | E1: Apr | F1: May | G1: Jun | H1: Jul | I1: Aug | J1: Sep | K1: Oct | L1: Nov | M1: Dec | N1: Total
A2: GrossRevenue | B2: =RawData!B2*RawData!B3 | C2: =RawData!C2*RawData!C3 | D2: =RawData!D2*RawData!D3 | E2: =RawData!E2*RawData!E3 | F2: =RawData!F2*RawData!F3 | G2: =RawData!G2*RawData!G3 | H2: =RawData!H2*RawData!H3 | I2: =RawData!I2*RawData!I3 | ... M2: =RawData!M2*RawData!M3 | N2: =SUM(B2:M2)
A3: DiscountedGross | B3: =IF(RawData!B2>1000, Revenue!B2*0.9, Revenue!B2) | C3: =IF(RawData!C2>1000, Revenue!C2*0.9, Revenue!C2) | D3: =IF(RawData!D2>1000, Revenue!D2*0.9, Revenue!D2) | E3: =IF(RawData!E2>1000, Revenue!E2*0.9, Revenue!E2) | F3: =IF(RawData!F2>1000, Revenue!F2*0.9, Revenue!F2) | G3: =IF(RawData!G2>1000, Revenue!G2*0.9, Revenue!G2) | H3: =IF(RawData!H2>1000, Revenue!H2*0.9, Revenue!H2) | I3: =IF(RawData!I2>1000, Revenue!I2*0.9, Revenue!I2) | ... M3: =IF(RawData!M2>1000, Revenue!M2*0.9, Revenue!M2) | N3: =SUM(B3:M3)
A4: SeasonFactor | B4: =VLOOKUP(RawData!B6, Rate!A2:B13, 2, FALSE) | C4: =VLOOKUP(RawData!C6, Rate!A2:B13, 2, FALSE) | D4: =VLOOKUP(RawData!D6, Rate!A2:B13, 2, FALSE) | E4: =VLOOKUP(RawData!E6, Rate!A2:B13, 2, FALSE) | F4: =VLOOKUP(RawData!F6, Rate!A2:B13, 2, FALSE) | G4: =VLOOKUP(RawData!G6, Rate!A2:B13, 2, FALSE) | H4: =VLOOKUP(RawData!H6, Rate!A2:B13, 2, FALSE) | I4: =VLOOKUP(RawData!I6, Rate!A2:B13, 2, FALSE) | J4: =VLOOKUP(RawData!J6, Rate!A2:B13, 2, FALSE) | K4: =VLOOKUP(RawData!K6, Rate!A2:B13, 2, FALSE) | L4: =VLOOKUP(RawData!L6, Rate!A2:B13, 2, FALSE) | M4: =VLOOKUP(RawData!M6, Rate!A2:B13, 2, FALSE) | N4: =SUM(B4:M4)

Sheet Cost
A1: Label | B1: Jan | C1: Feb | D1: Mar | E1: Apr | F1: May | G1: Jun | H1: Jul | I1: Aug | J1: Sep | K1: Oct | L1: Nov | M1: Dec | N1: Total
A2: TotalCost | B2: =RawData!B2*RawData!B4+RawData!B5 | C2: =RawData!C2*RawData!C4+RawData!C5 | D2: =RawData!D2*RawData!D4+RawData!D5 | E2: =RawData!E2*RawData!E4+RawData!E5 | F2: =RawData!F2*RawData!F4+RawData!F5 | G2: =RawData!G2*RawData!G4+RawData!G5 | H2: =RawData!H2*RawData!H4+RawData!H5 | I2: =RawData!I2*RawData!I4+RawData!I5 | ... M2: =RawData!M2*RawData!M4+RawData!M5 | N2: =SUM(B2:M2)

Sheet P&L
A1: Label | B1: Jan | C1: Feb | D1: Mar | E1: Apr | F1: May | G1: Jun | H1: Jul | I1: Aug | J1: Sep | K1: Oct | L1: Nov | M1: Dec | N1: Total
A2: GrossProfit | B2: =Revenue!B2-Cost!B2 | C2: =Revenue!C2-Cost!C2 | D2: =Revenue!D2-Cost!D2 | E2: =Revenue!E2-Cost!E2 | F2: =Revenue!F2-Cost!F2 | G2: =Revenue!G2-Cost!G2 | H2: =Revenue!H2-Cost!H2 | I2: =Revenue!I2-Cost!I2 | ... M2: =Revenue!M2-Cost!M2 | N2: =SUM(B2:M2)
A3: Tax | B3: ='P&L'!B2*0.25 | C3: ='P&L'!C2*0.25 | D3: ='P&L'!D2*0.25 | E3: ='P&L'!E2*0.25 | F3: ='P&L'!F2*0.25 | G3: ='P&L'!G2*0.25 | H3: ='P&L'!H2*0.25 | I3: ='P&L'!I2*0.25 | ... M3: ='P&L'!M2*0.25 | N3: =SUM(B3:M3)
A4: NetProfit | B4: ='P&L'!B2-'P&L'!B3 | C4: ='P&L'!C2-'P&L'!C3 | D4: ='P&L'!D2-'P&L'!D3 | E4: ='P&L'!E2-'P&L'!E3 | F4: ='P&L'!F2-'P&L'!F3 | G4: ='P&L'!G2-'P&L'!G3 | H4: ='P&L'!H2-'P&L'!H3 | I4: ='P&L'!I2-'P&L'!I3 | ... M4: ='P&L'!M2-'P&L'!M3 | N4: =SUM(B4:M4)

Sheet Dashboard
A1: Label | B1: Jan | C1: Feb | D1: Mar | E1: Apr | F1: May | G1: Jun | H1: Jul | I1: Aug | J1: Sep | K1: Oct | L1: Nov | M1: Dec | N1: Total
A2: NetProfit | B2: ='P&L'!B4 | C2: ='P&L'!C4 | D2: ='P&L'!D4 | E2: ='P&L'!E4 | F2: ='P&L'!F4 | G2: ='P&L'!G4 | H2: ='P&L'!H4 | I2: ='P&L'!I4 | ... M2: ='P&L'!M4 | N2: =SUM(B2:M2)
A3: Revenue | B3: =Revenue!B2 | C3: =Revenue!C2 | D3: =Revenue!D2 | E3: =Revenue!E2 | F3: =Revenue!F2 | G3: =Revenue!G2 | H3: =Revenue!H2 | I3: =Revenue!I2 | ... M3: =Revenue!M2 | N3: =SUM(B3:M3)
A4: Cost | B4: =Cost!B2 | C4: =Cost!C2 | D4: =Cost!D2 | E4: =Cost!E2 | F4: =Cost!F2 | G4: =Cost!G2 | H4: =Cost!H2 | I4: =Cost!I2 | ... M4: =Cost!M2 | N4: =SUM(B4:M4)

Sheet Rate
A1: MonthNo | B1: Factor
A2: 1 | B2: 1
A3: 2 | B3: 0.99
A4: 3 | B4: 0.98
A5: 4 | B5: 0.97
A6: 5 | B6: 0.96
A7: 6 | B7: 0.95
A8: 7 | B8: 0.94
A9: 8 | B9: 0.93
A10: 9 | B10: 0.92
A11: 10 | B11: 0.91
A12: 11 | B12: 0.9
A13: 12 | B13: 0.89

Sheet Agg
A1: Label | B1: M1 | C1: M2 | D1: M3 | E1: M4 | F1: M5 | G1: M6 | H1: M7 | I1: M8 | J1: M9 | K1: M10 | L1: M11 | M1: M12 | N1: Total
A2: Line1 | B2: ='Revenue'!B2 | C2: ='Revenue'!C2 | D2: ='Revenue'!D2 | E2: ='Revenue'!E2 | F2: ='Revenue'!F2 | G2: ='Revenue'!G2 | H2: ='Revenue'!H2 | I2: ='Revenue'!I2 | ... M2: ='Revenue'!M2 | N2: =MIN(B2:M2)
A3: Line2 | B3: ='Cost'!B2 | C3: ='Cost'!C2 | D3: ='Cost'!D2 | E3: ='Cost'!E2 | F3: ='Cost'!F2 | G3: ='Cost'!G2 | H3: ='Cost'!H2 | I3: ='Cost'!I2 | ... M3: ='Cost'!M2 | N3: =MAX(B3:M3)
A4: Line3 | B4: ='P&L'!B2 | C4: ='P&L'!C2 | D4: ='P&L'!D2 | E4: ='P&L'!E2 | F4: ='P&L'!F2 | G4: ='P&L'!G2 | H4: ='P&L'!H2 | I4: ='P&L'!I2 | ... M4: ='P&L'!M2 | N4: =AVERAGE(B4:M4)
A5: Line4 | B5: ='Dashboard'!B2 | C5: ='Dashboard'!C2 | D5: ='Dashboard'!D2 | E5: ='Dashboard'!E2 | F5: ='Dashboard'!F2 | G5: ='Dashboard'!G2 | H5: ='Dashboard'!H2 | I5: ='Dashboard'!I2 | ... M5: ='Dashboard'!M2 | N5: =SUMIF(B5:M5, ">=700", B5:M5)
A6: Line5 | B6: ='RawData'!B2 | C6: ='RawData'!C2 | D6: ='RawData'!D2 | E6: ='RawData'!E2 | F6: ='RawData'!F2 | G6: ='RawData'!G2 | H6: ='RawData'!H2 | I6: ='RawData'!I2 | ... M6: ='RawData'!M2 | N6: 7

Sheet Lk
A1: FactorLookup
B2: =VLOOKUP(C2, C2:D2, 2, FALSE) | C2: 1 | D2: 0.51
B3: =VLOOKUP(C3, C3:D3, 2, FALSE) | C3: 2 | D3: 0.52
B4: =VLOOKUP(C4, C4:D4, 2, FALSE) | C4: 3 | D4: 0.53
B5: =VLOOKUP(C5, C5:D5, 2, FALSE) | C5: 4 | D5: 0.54
B6: =VLOOKUP(C6, C6:D6, 2, FALSE) | C6: 5 | D6: 0.55
B7: =VLOOKUP(C7, C7:D7, 2, FALSE) | C7: 6 | D7: 0.56
B8: =VLOOKUP(C8, C8:D8, 2, FALSE) | C8: 7 | D8: 0.57
B9: =VLOOKUP(C9, C9:D9, 2, FALSE) | C9: 8 | D9: 0.58
B10: =VLOOKUP(C10, C10:D10, 2, FALSE) | C10: 9 | D10: 0.59
B11: =VLOOKUP(C11, C11:D11, 2, FALSE) | C11: 10 | D11: 0.6
B12: =VLOOKUP(C12, C12:D12, 2, FALSE) | C12: 11 | D12: 0.61
B13: =VLOOKUP(C13, C13:D13, 2, FALSE) | C13: 12 | D13: 0.62
