Workbook

Sheet RawData
A1: Label | B1: Jan | C1: Feb | D1: Mar | E1: Apr | F1: May | G1: Jun | H1: Jul | I1: Aug | J1: Sep | K1: Oct | L1: Nov | M1: Dec
A2: Units | B2: 997 | C2: 1188 | D2: 1015 | E2: 820 | F2: 932 | G2: 1061 | H2: 1048 | I2: 1007 | J2: 955 | K2: 1044 | L2: 983 | M2: 1098
A3: UnitPrice | B3: 62.83 | C3: 49.37 | D3: 47.79 | E3: 47.79 | F3: 46.9 | G3: 60.99 | H3: 64.75 | I3: 55.65 | J3: 59.1 | K3: 57.04 | L3: 47.94 | M3: 46.98
A4: UnitCost | B4: 26.11 | C4: 37.76 | D4: 29.95 | E4: 33.4 | F4: 30.31 | G4: 29.74 | H4: 34.61 | I4: 28.07 | J4: 33.29 | K4: 31.64 | L4: 32.82 | M4: 25.93
A5: Opex | B5: 9494 | C5: 5115 | D5: 5764 | E5: 10895 | F5: 11882 | G5: 8267 | H5: 10818 | I5: 11757 | J5: 11431 | K5: 10473 | L5: 10122 | M5: 5009

Sheet Revenue
A1: Label | B1: Jan | C1: Feb | D1: Mar | E1: Apr | F1: May | G1: Jun | H1: Jul | I1: Aug | J1: Sep | K1: Oct | L1: Nov | M1: Dec | N1: Total
A2: GrossRevenue | B2: =RawData!B2*RawData!B3 | C2: =RawData!C2*RawData!C3 | D2: =RawData!D2*RawData!D3 | E2: =RawData!E2*RawData!E3 | F2: =RawData!F2+RawData!F3 | G2: =RawData!G2*RawData!G3 | H2: =RawData!H2*RawData!H3 | I2: =RawData!I2*RawData!I3 | J2: =RawData!J2*RawData!J3 | K2: =RawData!K2*RawData!K3 | L2: =RawData!L2*RawData!L3 | M2: =RawData!M2*RawData!M3 | N2: =SUM(B2:M2)

Sheet Cost
A1: Label | B1: Jan | C1: Feb | D1: Mar | E1: Apr | F1: May | G1: Jun | H1: Jul | I1: Aug | J1: Sep | K1: Oct | L1: Nov | M1: Dec | N1: Total
A2: TotalCost | B2: =RawData!B2*RawData!B4+RawData!B5 | C2: =RawData!C2*RawData!C4+RawData!C5 | D2: =RawData!D2*RawData!D4+RawData!D5 | E2: =RawData!E2*RawData!E4+RawData!E5 | F2: =RawData!F2*RawData!F4-RawData!F5 | G2: =RawData!G2*RawData!G4+RawData!G5 | H2: =RawData!H2*RawData!H4+RawData!H5 | I2: =RawData!I2*RawData!I4+RawData!I5 | J2: =RawData!J2*RawData!J4+RawData!J5 | K2: =RawData!K2*RawData!K4+RawData!K5 | L2: =RawData!L2*RawData!L4+RawData!L5 | M2: =RawData!M2*RawData!M4+RawData!M5 | N2: =SUM(B2:M2)

Sheet P&L
A1: Label | B1: Jan | C1: Feb | D1: Mar | E1: Apr | F1: May | G1: Jun | H1: Jul | I1: Aug | J1: Sep | K1: Oct | L1: Nov | M1: Dec | N1: Total
A2: GrossProfit | B2: =Revenue!B2-Cost!B2 | C2: =Revenue!C2-Cost!C2 | D2: =Revenue!D2-Cost!D2 | E2: =Revenue!E2-Cost!E2 | F2: =Revenue!F2-Cost!F2 | G2: =Revenue!G2-Cost!G2 | H2: =Revenue!H2-Cost!H2 | I2: =Revenue!I2-Cost!I2 | ... M2: =Revenue!M2-Cost!M2 | N2: =SUM(B2:M2)
A3: Tax | B3: ='P&L'!B2*0.25 | C3: ='P&L'!C2*0.25 | D3: ='P&L'!D2*0.25 | E3: ='P&L'!E2*0.25 | F3: ='P&L'!F2*0.25 | G3: ='P&L'!G2*0.25 | H3: ='P&L'!H2*0.25 | I3: ='P&L'!I2*0.25 | ... M3: ='P&L'!M2*0.25 | N3: =SUM(B3:M3)
A4: NetProfit | B4: ='P&L'!B2-'P&L'!B3 | C4: ='P&L'!C2-'P&L'!C3 | D4: ='P&L'!D2-'P&L'!D3 | E4: ='P&L'!E2-'P&L'!E3 | F4: ='P&L'!F2-'P&L'!F3 | G4: ='P&L'!G2-'P&L'!G3 | H4: ='P&L'!H2-'P&L'!H3 | I4: ='P&L'!I2-'P&L'!I3 | ... M4: ='P&L'!M2-'P&L'!M3 | N4: =SUM(B4:M4)

Sheet Dashboard
A1: Label | B1: Jan | C1: Feb | D1: Mar | E1: Apr | F1: May | G1: Jun | H1: Jul | I1: Aug | J1: Sep | K1: Oct | L1: Nov | M1: Dec | N1: Total
A2: NetProfit | B2: ='P&L'!B4 | C2: ='P&L'!C4 | D2: ='P&L'!D4 | E2: ='P&L'!E4 | F2: ='P&L'!F4 | G2: ='P&L'!G4 | H2: ='P&L'!H4 | I2: ='P&L'!I4 | ... M2: ='P&L'!M4 | N2: =SUM(B2:M2)
A3: Revenue | B3: =Revenue!B2 | C3: =Revenue!C2 | D3: =Revenue!D2 | E3: =Revenue!E2 | F3: =Revenue!F2 | G3: =Revenue!G2 | H3: =Revenue!H2 | I3: =Revenue!I2 | ... M3: =Revenue!M2 | N3: =SUM(B3:M3)
A4: Cost | B4: =Cost!B2 | C4: =Cost!C2 | D4: =Cost!D2 | E4: =Cost!E2 | F4: =Cost!F2 | G4: =Cost!G2 | H4: =Cost!H2 | I4: =Cost!I2 | ... M4: =Cost!M2 | N4: =SUM(B4:M4)
